colab_or_not/__init__.py
colab_or_not/core.py
colab_or_not-0.4.0.dist-info/LICENSE
colab_or_not-0.4.0.dist-info/METADATA
colab_or_not-0.4.0.dist-info/WHEEL
colab_or_not-0.4.0.dist-info/top_level.txt
colab_or_not-0.4.0.dist-info/RECORD
