Metadata-Version: 2.1
Name: colab-or-not
Version: 0.4.0
Summary: A Python package to help make Jupyter notebooks runnable in Colab or local environments.
Home-page: https://github.com/higherbar-ai/colab-or-not
Author: Christopher Robert
Author-email: crobert@higherbar.ai
License: Apache 2.0
Project-URL: Documentation, https://colab-or-not.readthedocs.io/
Requires-Python: >=3.10
License-File: LICENSE
Requires-Dist: requests ~=2.32.3
Requires-Dist: python-dotenv ~=1.0.1
Requires-Dist: ipython
Requires-Dist: ipywidgets
